{"is_source_file": true, "format": "JavaScript (React JSX)", "description": "React component for the main application interface of a game, including theme toggling, mode switching between 2D and 3D, and rendering game components.", "external_files": ["./components/GameCanvas", "./components/Game3D", "./App.css"], "external_methods": ["React.useState", "React.useEffect"], "published": ["App"], "classes": [], "methods": [{"name": "App", "description": "Main React functional component managing game UI, theme, mode, and state."}], "calls": ["React.useState", "React.useEffect", "setInterval", "clearInterval", "document.documentElement.setAttribute", "setTheme", "setMode3D", "setScore", "setTime", "Game3D", "GameCanvas"], "search-terms": ["React", "GameCanvas", "Game3D", "theme toggle", "mode switch", "App component", "main game interface", "UI styling", "score and time display"], "state": 2, "file_id": 9, "knowledge_revision": 55, "git_revision": "46cce1d7c8203b0cbc14afb6c0e8d51038785192", "revision_history": [{"25": "6c6ba2e83cb90c020089bbbea168a35489d72dab"}, {"28": "6c6ba2e83cb90c020089bbbea168a35489d72dab"}, {"31": "f9f275255cd1c66284a2f8428e0db7b814b41ea3"}, {"41": "6330577d9709aa7f57c080243f9ffbd5164ca97b"}, {"55": "46cce1d7c8203b0cbc14afb6c0e8d51038785192"}], "ctags": [], "filename": "dream_dash_frontend/src/App.js", "format-version": 4, "code-base-name": "https://github.com/kavia-common/dream-sky-adventure-222321-222345.git:kavia-main"}